{
  "0": {
    "end_frame": 2187,
    "event_type": "vehicle_turns_left",
    "identity": 20679,
    "objects": {},
    "start_frame": 2097,
    "trajectory": {
      "2097": [
        788.5,
        971.0,
        1099.5,
        1068.5
      ],
      "2102": [
        795.0,
        981.0,
        1069.0,
        1065.0
      ],
      "2107": [
        776.6666666666666,
        971.3333333333334,
        1046.0,
        1068.0
      ],
      "2112": [
        759.0,
        975.5,
        1067.0,
        1071.5
      ],
      "2117": [
        743.5,
        968.0,
        1060.5,
        1074.0
      ],
      "2122": [
        719.0,
        960.0,
        1058.5,
        1074.5
      ],
      "2127": [
        686.0,
        945.3333333333334,
        1046.0,
        1070.6666666666667
      ],
      "2132": [
        705.3333333333334,
        958.6666666666666,
        1042.6666666666667,
        1068.0
      ],
      "2137": [
        668.8,
        941.2,
        1017.2,
        1071.2
      ],
      "2142": [
        660.0,
        943.3333333333334,
        958.6666666666666,
        1070.0
      ],
      "2147": [
        623.0,
        912.0,
        971.0,
        1065.0
      ],
      "2152": [
        607.6,
        923.2,
        953.2,
        1071.2
      ],
      "2157": [
        594.8,
        909.6,
        952.4,
        1068.0
      ],
      "2162": [
        593.3333333333334,
        905.3333333333334,
        942.6666666666666,
        1070.0
      ],
      "2167": [
        498.4,
        884.4,
        929.6,
        1070.4
      ],
      "2172": [
        506.4,
        874.0,
        903.2,
        1060.8
      ],
      "2177": [
        463.5,
        875.0,
        887.0,
        1071.0
      ],
      "2182": [
        461.5,
        888.0,
        861.0,
        1069.5
      ],
      "2187": [
        436.5,
        893.5,
        818.5,
        1064.5
      ]
    }
  },
  "1": {
    "end_frame": 4912,
    "event_type": "person_talks_to_person",
    "identity": 20680,
    "objects": {},
    "start_frame": 4245,
    "trajectory": {
      "4245": [
        6.0,
        753.0,
        194.0,
        933.0
      ],
      "4268": [
        5.0,
        728.0,
        173.0,
        925.0
      ],
      "4291": [
        5.0,
        742.0,
        212.0,
        945.0
      ],
      "4314": [
        5.0,
        749.0,
        181.0,
        931.0
      ],
      "4337": [
        4.0,
        756.0,
        214.0,
        956.0
      ],
      "4360": [
        3.0,
        741.0,
        207.0,
        939.0
      ],
      "4383": [
        4.0,
        741.0,
        199.0,
        941.0
      ],
      "4406": [
        5.0,
        747.0,
        201.0,
        948.0
      ],
      "4429": [
        1.0,
        741.0,
        202.0,
        942.0
      ],
      "4452": [
        5.0,
        734.0,
        206.0,
        928.0
      ],
      "4475": [
        8.0,
        736.0,
        201.0,
        942.0
      ],
      "4498": [
        2.0,
        750.0,
        180.0,
        937.0
      ],
      "4521": [
        2.0,
        731.0,
        190.0,
        948.0
      ],
      "4544": [
        3.0,
        740.0,
        187.0,
        938.0
      ],
      "4567": [
        4.666666666666667,
        756.0,
        150.0,
        894.6666666666666
      ],
      "4590": [
        5.0,
        750.0,
        187.0,
        968.0
      ],
      "4613": [
        5.0,
        752.0,
        203.0,
        936.0
      ],
      "4636": [
        0.0,
        749.0,
        192.0,
        963.0
      ],
      "4659": [
        7.0,
        741.0,
        203.0,
        926.0
      ],
      "4682": [
        4.0,
        750.0,
        225.0,
        954.0
      ],
      "4705": [
        4.0,
        751.0,
        211.0,
        930.0
      ],
      "4728": [
        2.0,
        755.0,
        211.0,
        928.0
      ],
      "4751": [
        6.0,
        763.0,
        227.0,
        936.0
      ],
      "4774": [
        7.333333333333333,
        755.3333333333334,
        179.33333333333334,
        914.6666666666666
      ],
      "4797": [
        16.0,
        759.0,
        138.0,
        910.5
      ],
      "4820": [
        6.0,
        744.0,
        182.0,
        926.0
      ],
      "4843": [
        4.0,
        751.0,
        172.0,
        928.0
      ],
      "4866": [
        6.0,
        745.0,
        168.0,
        917.0
      ],
      "4889": [
        10.0,
        766.6666666666666,
        156.66666666666666,
        905.3333333333334
      ],
      "4912": [
        8.0,
        755.0,
        207.0,
        917.0
      ]
    }
  },
  "2": {
    "end_frame": 3975,
    "event_type": "vehicle_stops",
    "identity": 41148,
    "objects": {},
    "start_frame": 3905,
    "trajectory": {
      "3905": [
        12.666666666666666,
        786.0,
        74.0,
        892.6666666666666
      ],
      "3910": [
        2.0,
        788.0,
        83.0,
        884.0
      ],
      "3920": [
        5.333333333333333,
        740.6666666666666,
        128.66666666666666,
        919.3333333333334
      ],
      "3925": [
        4.0,
        752.0,
        134.66666666666666,
        916.6666666666666
      ],
      "3930": [
        2.6666666666666665,
        750.6666666666666,
        130.66666666666666,
        905.3333333333334
      ],
      "3935": [
        6.666666666666667,
        728.6666666666666,
        138.66666666666666,
        914.6666666666666
      ],
      "3940": [
        2.6666666666666665,
        735.3333333333334,
        145.33333333333334,
        910.0
      ],
      "3945": [
        3.3333333333333335,
        755.3333333333334,
        143.33333333333334,
        905.3333333333334
      ],
      "3950": [
        6.666666666666667,
        745.3333333333334,
        160.66666666666666,
        919.3333333333334
      ],
      "3955": [
        10.0,
        748.6666666666666,
        159.33333333333334,
        916.0
      ],
      "3960": [
        6.0,
        756.0,
        168.66666666666666,
        922.0
      ],
      "3965": [
        15.333333333333334,
        740.0,
        160.66666666666666,
        918.6666666666666
      ],
      "3970": [
        9.333333333333334,
        743.3333333333334,
        137.33333333333334,
        912.0
      ],
      "3975": [
        7.333333333333333,
        749.3333333333334,
        170.0,
        944.0
      ]
    }
  }
}